CoNSEPT/CNN.py
CoNSEPT/DataBuilder.py
CoNSEPT/Dataset.py
CoNSEPT/S2E.py
CoNSEPT/__init__.py
CoNSEPT/train.py
CoNSEPT/utils.py
CoNSEPT-0.5.0.dist-info/LICENSE
CoNSEPT-0.5.0.dist-info/METADATA
CoNSEPT-0.5.0.dist-info/WHEEL
CoNSEPT-0.5.0.dist-info/entry_points.txt
CoNSEPT-0.5.0.dist-info/top_level.txt
CoNSEPT-0.5.0.dist-info/RECORD
