Metadata-Version: 2.1
Name: CoNSEPT
Version: 0.5.0
Summary: A Convolutional Neural Network-based Sequence-to-Expression Prediction Tool
Home-page: https://github.com/PayamDiba/CoNSEPT
Author: Payam Dibaeinia
Author-email: dibaein2@illinois.edu
License: MIT License
Platform: UNKNOWN
Requires-Python: >3.5.2
Requires-Dist: tensorflow (>=2.3)
Requires-Dist: numpy
Requires-Dist: pandas
